Metadata-Version: 2.1
Name: streamlit-lightweight-charts
Version: 0.7.20
Summary: Wrapper for TradingView `lightweight-charts`
Home-page: https://github.com/freyastreamlit/streamlit-lightweight-charts
Author: Joe Rosa
Author-email: joe.rosa@itpmngt.co.uk
License: MIT
Platform: UNKNOWN
Classifier: License :: OSI Approved :: MIT License
Classifier: Programming Language :: Python :: 3
Classifier: Programming Language :: Python :: 3.6
Requires-Python: >=3.6
